.travis.yml
MANIFEST.in
flask_multisession.py
requirements.txt
setup.py
Flask_Multi_Session.egg-info/PKG-INFO
Flask_Multi_Session.egg-info/SOURCES.txt
Flask_Multi_Session.egg-info/dependency_links.txt
Flask_Multi_Session.egg-info/not-zip-safe
Flask_Multi_Session.egg-info/requires.txt
Flask_Multi_Session.egg-info/top_level.txt