Metadata-Version: 1.1
Name: Flask-Multi-Session
Version: 0.1.7
Summary: Redis multi-sessions for Flask apps
Home-page: https://github.com/atkin1450/flask-multi-session
Author: Nikita Bobrov
Author-email: atkin1450@gmail.com
License: MIT
Platform: any
Classifier: Development Status :: 5 - Production/Stable
Classifier: Environment :: Web Environment
Classifier: Intended Audience :: Developers
Classifier: License :: OSI Approved :: MIT License
Classifier: Operating System :: OS Independent
Classifier: Programming Language :: Python
Classifier: Topic :: Internet :: WWW/HTTP :: Dynamic Content
Classifier: Topic :: Software Development :: Libraries :: Python Modules
